tidy_headers/VERSION
tidy_headers/__init__.py
tidy_headers/__version__.py
tidy_headers/_eval.py
tidy_headers/_main.py
tidy_headers/_parse_array.py
tidy_headers/_parse_item.py
tidy_headers-1.0.4.dist-info/LICENSE
tidy_headers-1.0.4.dist-info/LICENSE.txt
tidy_headers-1.0.4.dist-info/WHEEL
tidy_headers-1.0.4.dist-info/METADATA
tidy_headers-1.0.4.dist-info/RECORD
