Metadata-Version: 2.1
Name: tidy_headers
Version: 1.0.4
Summary: Easy headers, inspired by the tidy data specification.
Home-page: https://github.com/untzag/tidy_headers
Author: Blaise Thompson
Author-email: blaise@untzag.com
Requires-Python: >3.8
Classifier: Development Status :: 5 - Production/Stable
Classifier: Intended Audience :: Science/Research
Classifier: License :: OSI Approved :: MIT License
Classifier: Natural Language :: English
Classifier: Programming Language :: Python :: 3
Classifier: Topic :: Scientific/Engineering
Requires-Dist: numpy
Requires-Dist: black ; extra == "dev"
Requires-Dist: pre-commit ; extra == "dev"
Requires-Dist: pytest ; extra == "dev"
Requires-Dist: pytest-cov ; extra == "dev"
Provides-Extra: dev
